<?xml version="1.0" encoding="utf-8"?>
<beans>
    <bean name="student" class="com.wang.entity.Student" >
        <property name="name" value="123"></property>
    </bean>

    <bean name="teacher" class="com.wang.entity.Teacher">
        <property name="student" ref="student"></property>
    </bean>
    <bean name="person" class="com.wang.entity.Person" scope="prototype">
        <property name="teacher" ref="teacher"></property>
        <property name="student" ref="student"></property>
    </bean>

</beans>